cloud_logger/__init__.py
cloud_logger2-2020.7.0.dist-info/LICENSE
cloud_logger2-2020.7.0.dist-info/METADATA
cloud_logger2-2020.7.0.dist-info/WHEEL
cloud_logger2-2020.7.0.dist-info/top_level.txt
cloud_logger2-2020.7.0.dist-info/RECORD
