Metadata-Version: 2.1
Name: cloud-logger2
Version: 2020.7.0
Summary: An experimental lightweight logger
Home-page: https://github.com/artemdevel/cloud_logger
Author: artemdevel
Author-email: artem.devel2014@gmail.com
License: UNKNOWN
Platform: UNKNOWN
Classifier: Intended Audience :: Developers
Classifier: Topic :: Software Development :: Build Tools
Classifier: Programming Language :: Python :: 3
Classifier: License :: OSI Approved :: GNU General Public License v3 (GPLv3)
Classifier: Operating System :: OS Independent
Requires-Python: >=3.5
